excel_toolbox/__init__.py
excel_toolbox/cleaner.py
excel_toolbox/cli.py
excel_toolbox/converter.py
excel_toolbox/merger.py
excel_toolbox-1.0.0.dist-info/licenses/LICENSE
excel_toolbox-1.0.0.dist-info/METADATA
excel_toolbox-1.0.0.dist-info/WHEEL
excel_toolbox-1.0.0.dist-info/entry_points.txt
excel_toolbox-1.0.0.dist-info/top_level.txt
excel_toolbox-1.0.0.dist-info/RECORD
