Metadata-Version: 2.4
Name: excel-toolbox
Version: 1.0.0
Summary: 一体化 Excel 数据处理工具集 - 数据整合、清洗、转换全流程解决方案
Author-email: Chandler <275737875@qq.com>
License: MIT
Project-URL: Homepage, https://github.com/yourusername/excel-toolbox
Project-URL: Documentation, https://github.com/yourusername/excel-toolbox#readme
Project-URL: Repository, https://github.com/yourusername/excel-toolbox
Keywords: excel,data-processing,csv,json,pandas
Classifier: Development Status :: 5 - Production/Stable
Classifier: Intended Audience :: Developers
Classifier: License :: OSI Approved :: MIT License
Classifier: Programming Language :: Python :: 3
Classifier: Programming Language :: Python :: 3.9
Classifier: Programming Language :: Python :: 3.10
Classifier: Programming Language :: Python :: 3.11
Classifier: Programming Language :: Python :: 3.12
Requires-Python: >=3.9
License-File: LICENSE
Requires-Dist: pandas>=2.0.0
Requires-Dist: openpyxl>=3.1.0
Requires-Dist: xlrd>=2.0.0
Requires-Dist: typer>=0.9.0
Requires-Dist: rich>=13.0.0
Dynamic: license-file
